hl7v2GenomicsExtractor/__init__.py
hl7v2GenomicsExtractor/common.py
hl7v2GenomicsExtractor/converter.py
hl7v2GenomicsExtractor/gene_ref_seq.py
hl7v2GenomicsExtractor/hl7v2_helper.py
hl7v2GenomicsExtractor/hl7v2_message_generator.py
hl7v2GenomicsExtractor-0.0.4.dist-info/LICENSE
hl7v2GenomicsExtractor-0.0.4.dist-info/METADATA
hl7v2GenomicsExtractor-0.0.4.dist-info/WHEEL
hl7v2GenomicsExtractor-0.0.4.dist-info/top_level.txt
hl7v2GenomicsExtractor-0.0.4.dist-info/RECORD
