Metadata-Version: 2.1
Name: hl7v2GenomicsExtractor
Version: 0.0.4
Summary: Convert vcf/xml files to HL7V2 message
Home-page: https://github.com/HL7V2-Genomics-Conversion-Utilities/hl7v2GenomicsExtractor
Author: ""
Author-email: rohaninjmu@gmail.com
License: Apache Software License
Classifier: Programming Language :: Python :: 3
Classifier: Operating System :: OS Independent
Classifier: License :: OSI Approved :: Apache Software License
License-File: LICENSE
Requires-Dist: Cython (==0.29.21)
Requires-Dist: hl7apy (==1.3.4)
Requires-Dist: pysam
Requires-Dist: pandas
Requires-Dist: pytz (==2019.3)
Requires-Dist: pyranges (==0.0.96)
Requires-Dist: xmltodict (==0.13.0)
Requires-Dist: PyVCF3 (==1.0.3)
